LICENSE.txt
README.rst
setup.cfg
setup.py
src/miqatools/__init__.py
src/miqatools.egg-info/PKG-INFO
src/miqatools.egg-info/SOURCES.txt
src/miqatools.egg-info/dependency_links.txt
src/miqatools.egg-info/requires.txt
src/miqatools.egg-info/top_level.txt
src/miqatools/datamanagement/__init__.py
src/miqatools/datamanagement/datasethelpers/__init__.py
src/miqatools/remoteexecution/__init__.py
src/miqatools/remoteexecution/adhoc_execution/__init__.py
src/miqatools/remoteexecution/adhoc_testing/__init__.py
src/miqatools/remoteexecution/baseuploadhelpers/__init__.py
src/miqatools/remoteexecution/executionhelpers/__init__.py
src/miqatools/remoteexecution/offlineexecution/__init__.py
src/miqatools/remoteexecution/triggertest_helpers/__init__.py
src/miqatools/remoteexecution/triggertestandupload_dockercmd/__init__.py
src/miqatools/remoteexecution/triggertestandupload_python/__init__.py
src/miqatools/remoteexecution/uploadhelpers/__init__.py
src/miqatools/utilities/__init__.py