Metadata-Version: 2.1
Name: miqatools
Version: 1.1.12
Home-page: https://www.magnalabs.co
Author: Gwenn Berry
Author-email: gwenn@magnalabs.co
License: GPLv3
Keywords: miqa
License-File: LICENSE.txt
Requires-Dist: asyncio
Requires-Dist: aiohttp
